Workbook

Sheet Assumptions
A3: Assumption: each 1 percentage-point change in completion changes annual contract volume by 1% relative to baseline, within the tested range. This relationship is unverified and assumes the effect occurs within the forecast year.
C4: Input | D4: Value
C5: Baseline annual programs | D5: 30
C6: Average program contract value | D6: 40000
C7: Basline completion rate | D7: 0.6
C8: Portal investment cost | D8: 130000
C10: Baseline annual revenue | D10: =D5*D6 -> 1200000
C12: Scenario Completion Rate | D12: 0.6
C13: Contract volume change per 1 percentage-point completion change | D13: 0.01
C18: Scenario annual programs | D18: =$D$5*(1+($D$12-$D$7)*100*$D$13) -> 30
C19: Scenario annual revenue | D19: =D18*$D$6 -> 1200000
C20: Additional annual revenue versus baseline | D20: =D19-D10 -> 0
A21: Revenue-recovery calculation excludes additional delivery and ongoing portal costs | C21: Additional revenue after portal investment | D21: =D20-$D$8 -> -130000
C22: Completion lift needed for revenue recovery in percentage points | D22: =$D$8/($D$10*$D$13) -> 10.833333
C23: Completion rate needed for revenue recovery | D23: =$D$7+D22/100 -> 0.70833333

Sheet Forecast
A1: 12 Month Revenue Forecast
C4: Months | D4: Baseline Revenue | E4: Scenario Revenue
C5: Month 1 | D5: =Assumptions!$D$10/12 -> 100000 | E5: =Assumptions!$D$19/12 -> 100000
C6: Month 2 | D6: =Assumptions!$D$10/12 -> 100000 | E6: =Assumptions!$D$19/12 -> 100000
C7: Month 3 | D7: =Assumptions!$D$10/12 -> 100000 | E7: =Assumptions!$D$19/12 -> 100000
C8: Month 4 | D8: =Assumptions!$D$10/12 -> 100000 | E8: =Assumptions!$D$19/12 -> 100000
C9: Month 5 | D9: =Assumptions!$D$10/12 -> 100000 | E9: =Assumptions!$D$19/12 -> 100000
C10: Month 6 | D10: =Assumptions!$D$10/12 -> 100000 | E10: =Assumptions!$D$19/12 -> 100000
C11: Month 7 | D11: =Assumptions!$D$10/12 -> 100000 | E11: =Assumptions!$D$19/12 -> 100000
C12: Month 8 | D12: =Assumptions!$D$10/12 -> 100000 | E12: =Assumptions!$D$19/12 -> 100000
C13: Month 9 | D13: =Assumptions!$D$10/12 -> 100000 | E13: =Assumptions!$D$19/12 -> 100000
C14: Month 10 | D14: =Assumptions!$D$10/12 -> 100000 | E14: =Assumptions!$D$19/12 -> 100000
C15: Month 11 | D15: =Assumptions!$D$10/12 -> 100000 | E15: =Assumptions!$D$19/12 -> 100000
C16: Month 12 | D16: =Assumptions!$D$10/12 -> 100000 | E16: =Assumptions!$D$19/12 -> 100000
C17: Annual Total | D17: =SUM(D5:D16) -> 1200000 | E17: =SUM(E5:E16) -> 1200000
C19: Assumption: annual contract revenue is spread evenly across 12 months because no monthly delivery or revenue schedule was supplied.

Sheet Scenarios 
B2: Scenario Summary
D3: Current Values: | E3: Base Scenario | F3: Best Scenario | G3: Worst Scenario
E4: Base Scenario | F4: Best Scenario | G4: Worst Scenario
B5: Changing Cells:
C6: Scenario completion rate | D6: 0.6 | E6: 0.6 | F6: 0.72 | G6: 0.55
B7: Result Cells:
C8: Expected annual programs | D8: 30 | E8: 30 | F8: 33.6 | G8: 28.5
C9: Annual revenue | D9: 1200000 | E9: 1200000 | F9: 1344000 | G9: 1140000
C10: Additional revenue vs baseline | D10: 0 | E10: 0 | F10: 144000 | G10: -60000
C11: additional revenue less investment | D11: -130000 | E11: -130000 | F11: 14000 | G11: -190000
C12: Required completion lift from the 60% baseline | D12: 10.833333 | E12: 10.833333 | F12: 10.833333 | G12: 10.833333
B13: Notes: Current Values column represents values of changing cells at
B14: time Scenario Summary Report was created. Changing cells for each
B15: scenario are highlighted in grey.
B18: Revenue recovery excludes additional delivery and ongoing portal costs. This summary is static and must be regenerated after model changes.

Sheet Sensitivity
C2: Annual Revenue Sensitivity
C4: =Assumptions!$D$5*(1+($D$13-Assumptions!$D$7)*100*Assumptions!$D$13)*$D$12 -> 1200000 | D4: 35000 | E4: 37500 | F4: 40000 | G4: 42500 | H4: 45000
C5: 0.55 | D5: 997500 | E5: 1068750 | F5: 1140000 | G5: 1211250 | H5: 1282500
C6: 0.6 | D6: 1050000 | E6: 1125000 | F6: 1200000 | G6: 1275000 | H6: 1350000
C7: 0.65 | D7: 1102500 | E7: 1181250 | F7: 1260000 | G7: 1338750 | H7: 1417500
C8: 0.7 | D8: 1155000 | E8: 1237500 | F8: 1320000 | G8: 1402500 | H8: 1485000
C9: 0.75 | D9: 1207500 | E9: 1293750 | F9: 1380000 | G9: 1466250 | H9: 1552500
C12: Test Contract Value | D12: =Assumptions!$D$6 -> 40000
C13: Test Completion Rate | D13: =Assumptions!$D$12 -> 0.6

Sheet Scenario Summary 1
B2: Scenario Summary
D3: Current Values: | E3: Base Scenario | F3: Best Scenario | G3: Worst Scenario
E4: Base Scenario | F4: Best Scenario | G4: Worst Scenario
B5: Changing Cells:
C6: $D$12 | D6: 0.72 | E6: 0.6 | F6: 0.72 | G6: 0.55
B7: Result Cells:
C8: $D$18 | D8: 33.6 | E8: 30 | F8: 33.6 | G8: 28.5
C9: $D$19 | D9: 1344000 | E9: 1200000 | F9: 1344000 | G9: 1140000
C10: $D$20 | D10: 144000 | E10: 0 | F10: 144000 | G10: -60000
B11: Notes: Current Values column represents values of changing cells at
B12: time Scenario Summary Report was created. Changing cells for each
B13: scenario are highlighted in grey.

Sheet Scenario Summary 2
B2: Scenario Summary
D3: Current Values: | E3: Base Scenario | F3: Best Scenario | G3: Worst Scenario
E4: Base Scenario | F4: Best Scenario | G4: Worst Scenario
B5: Changing Cells:
C6: $D$12 | D6: 0.6 | E6: 0.6 | F6: 0.72 | G6: 0.55
B7: Result Cells:
C8: $D$18 | D8: 30 | E8: 30 | F8: 33.6 | G8: 28.5
C9: $D$19 | D9: 1200000 | E9: 1200000 | F9: 1344000 | G9: 1140000
C10: $D$20 | D10: 0 | E10: 0 | F10: 144000 | G10: -60000
C11: $D$21
C12: $D$22 | D12: -130000 | E12: -130000 | F12: 14000 | G12: -190000
B13: Notes: Current Values column represents values of changing cells at
B14: time Scenario Summary Report was created. Changing cells for each
B15: scenario are highlighted in grey.
